django_warrant/__init__.py
django_warrant/backend.py
django_warrant/forms.py
django_warrant/middleware.py
django_warrant/models.py
django_warrant/tests.py
django_warrant/urls.py
django_warrant/utils.py
django_warrant/migrations/__init__.py
django_warrant/views/__init__.py
django_warrant/views/profile.py
django_warrant/views/subscriptions.py
django_warrant-0.1.0.dist-info/DESCRIPTION.rst
django_warrant-0.1.0.dist-info/METADATA
django_warrant-0.1.0.dist-info/RECORD
django_warrant-0.1.0.dist-info/WHEEL
django_warrant-0.1.0.dist-info/metadata.json
django_warrant-0.1.0.dist-info/top_level.txt
django_warrant-0.1.0.dist-info/zip-safe
