Metadata-Version: 2.0
Name: django-warrant
Version: 0.1.0
Summary: Django library that uses the warrant python utility library to provide authentication via AWS Cognito.
Home-page: https://github.com/MetaMetricsInc/django-warrant
Author: MetaMetrics
Author-email: engineering@lexile.com
License: GNU GPL V3
Keywords: aws,cognito,api,gateway,django
Platform: UNKNOWN
Classifier: Framework :: Django
Classifier: Framework :: Django :: 1.10
Classifier: Programming Language :: Python
Classifier: Topic :: Software Development :: Libraries :: Python Modules
Classifier: Environment :: Web Environment
Requires-Dist: Django (>=1.9)
Requires-Dist: django-braces (>=1.11.0)
Requires-Dist: django-crispy-forms (>=1.6.1)
Requires-Dist: django-extensions (>=1.7.7)
Requires-Dist: warrant (>=0.2.0)
